README.txt
setup.py
Fangorn.egg-info/PKG-INFO
Fangorn.egg-info/SOURCES.txt
Fangorn.egg-info/dependency_links.txt
Fangorn.egg-info/requires.txt
Fangorn.egg-info/top_level.txt
fangorn/__init__.py
fangorn/base.py
fangorn/benchmark.py
fangorn/ns.py
fangorn/compat/__init__.py
fangorn/compat/mysqldb.py
fangorn/compat/sqlite3.py
fangorn/test/__init__.py
fangorn/test/large.py
fangorn/test/small.py
fangorn/test/fixture/data.sql
fangorn/test/fixture/fixture.py
fangorn/test/fixture/mysql_schema.sql
fangorn/test/fixture/sqlite_schema.sql
fangorn/test/mysql/__init__.py
fangorn/test/mysql/large.py
fangorn/test/mysql/small.py
fangorn/test/sqlite/__init__.py
fangorn/test/sqlite/large.py
fangorn/test/sqlite/small.py