Metadata-Version: 1.1
Name: Fangorn
Version: 0.3.2
Summary: Nested Sets SQL Tree for Python
Home-page: https://bitbucket.org/saaj/fangorn
Author: saaj
Author-email: mail@saaj.me
License: LGPL-2.1+
Keywords: python tree nested-sets mysql sqlite
Platform: Any
Classifier: Topic :: Database
Classifier: Topic :: Software Development :: Libraries
Classifier: Programming Language :: Python :: 2
Classifier: Programming Language :: Python :: 2.7
Classifier: Programming Language :: Python :: 3
Classifier: Programming Language :: Python :: 3.3
Classifier: Programming Language :: Python :: 3.4
Classifier: Programming Language :: Python :: 3.5
Classifier: Programming Language :: Python :: 3.6
Classifier: Programming Language :: Python :: Implementation :: CPython
Classifier: Programming Language :: Python :: Implementation :: PyPy
Classifier: Intended Audience :: Developers
